fractalshades/__init__.py
fractalshades/core.py
fractalshades/db.py
fractalshades/log.py
fractalshades/mthreading.py
fractalshades/parallel_lock.py
fractalshades/perturbation.py
fractalshades/postproc.py
fractalshades/projection.py
fractalshades/settings.py
fractalshades/utils.py
fractalshades/colors/__init__.py
fractalshades/colors/color_mapping.py
fractalshades/colors/colormap_templates.py
fractalshades/colors/layers.py
fractalshades/colors/lighting_templates.py
fractalshades/data/LICENSE.txt
fractalshades/data/GidoleFont/Gidole-Regular.ttf
fractalshades/data/GidoleFont/Gidolinya-Regular.otf
fractalshades/data/GidoleFont/License.txt
fractalshades/data/GidoleFont/Readme+Characters.pdf
fractalshades/gui/QCodeEditor.py
fractalshades/gui/__init__.py
fractalshades/gui/guimodel.py
fractalshades/gui/guitemplates.py
fractalshades/gui/model.py
fractalshades/models/__init__.py
fractalshades/models/burning_ship.py
fractalshades/models/collatz.py
fractalshades/models/mandelbrot_M2.py
fractalshades/models/mandelbrot_Mn.py
fractalshades/models/power_tower.py
fractalshades/movie/__init__.py
fractalshades/movie/movie.py
fractalshades/mpmath_utils/FP_loop.cp310-win_amd64.pyd
fractalshades/mpmath_utils/FP_loop.pyx
fractalshades/numpy_utils/__init__.py
fractalshades/numpy_utils/expr_parser.py
fractalshades/numpy_utils/filters.py
fractalshades/numpy_utils/interp2d.py
fractalshades/numpy_utils/numba_xr.py
fractalshades/numpy_utils/xrange.py
fractalshades-1.2.1.dist-info/METADATA
fractalshades-1.2.1.dist-info/WHEEL
fractalshades-1.2.1.dist-info/top_level.txt
fractalshades-1.2.1.dist-info/RECORD
