Metadata-Version: 2.1
Name: fractalshades
Version: 1.2.1
Summary: Fractal deep-zoom explorer package for Mandelbrot fractal.
Home-page: https://github.com/GBillotey/Fractal-shades
Author: Geoffroy Billotey
Author-email: geoffroy.billotey@gmail.com
License: MIT
Project-URL: Documentation, https://gbillotey.github.io/Fractalshades/
Project-URL: Bug Tracker, https://github.com/GBillotey/Fractal-shades/issues
Classifier: Development Status :: 4 - Beta
Classifier: Programming Language :: Python :: 3
Classifier: License :: OSI Approved :: MIT License
Classifier: Operating System :: POSIX
Classifier: Operating System :: Microsoft :: Windows
Classifier: Topic :: Multimedia :: Graphics
Classifier: Topic :: Scientific/Engineering :: Mathematics
Requires-Python: >=3.8
Requires-Dist: numba>=0.52.0
Requires-Dist: mpmath>=1.1.0
Requires-Dist: gmpy2>=2.1.2
Requires-Dist: Pillow
Requires-Dist: PyQt6>=6.1.0
Requires-Dist: pygments>=2.9.0
Requires-Dist: wheel>=0.37.0
Requires-Dist: importlib-resources>1.3; python_version < "3.9"
